audiobackend/__init__.py
audiobackend/audiobackend.py
audiobackend-0.1.0.dist-info/LICENSE
audiobackend-0.1.0.dist-info/METADATA
audiobackend-0.1.0.dist-info/WHEEL
audiobackend-0.1.0.dist-info/top_level.txt
audiobackend-0.1.0.dist-info/RECORD
