Metadata-Version: 2.1
Name: audiobackend
Version: 0.1.0
Summary: High-quality audio playback library with DSD support and efficient buffer management
Author-email: Niamorro <niamorrodev@gmail.com>
License: GPL-3.0-or-later
Project-URL: Homepage, https://github.com/Niamorro/audiobackend
Project-URL: Documentation, https://niamorro.github.io/audiobackend/
Project-URL: Repository, https://github.com/Niamorro/audiobackend.git
Project-URL: Issues, https://github.com/Niamorro/audiobackend/issues
Keywords: audio,playback,DSD,sound,music,player,high-quality,buffer
Classifier: Development Status :: 3 - Alpha
Classifier: Intended Audience :: Developers
Classifier: License :: OSI Approved :: GNU General Public License v3 or later (GPLv3+)
Classifier: Programming Language :: Python :: 3 :: Only
Classifier: Programming Language :: Python :: 3.7
Classifier: Programming Language :: Python :: 3.8
Classifier: Programming Language :: Python :: 3.9
Classifier: Programming Language :: Python :: 3.10
Classifier: Programming Language :: Python :: 3.11
Classifier: Programming Language :: Python :: 3.12
Classifier: Programming Language :: Python :: 3.13
Classifier: Topic :: Multimedia :: Sound/Audio
Classifier: Topic :: Multimedia :: Sound/Audio :: Players
Classifier: Topic :: Software Development :: Libraries :: Python Modules
Classifier: Operating System :: OS Independent
Requires-Python: >=3.7
License-File: LICENSE
Requires-Dist: av>=10.0.0
Requires-Dist: sounddevice>=0.4.5
Requires-Dist: numpy>=1.20.0
Provides-Extra: dev
Requires-Dist: pytest>=7.0.0; extra == "dev"
Requires-Dist: pytest-cov>=4.0.0; extra == "dev"
Requires-Dist: build>=0.10.0; extra == "dev"
Requires-Dist: twine>=4.0.0; extra == "dev"
Requires-Dist: mkdocs-material>=9.0.0; extra == "dev"
Requires-Dist: mkdocs-git-revision-date-localized-plugin>=1.0.0; extra == "dev"
Requires-Dist: mkdocs-minify-plugin>=0.7.0; extra == "dev"
